weiroll.py
weiroll_py-0.2.2.dist-info/LICENSE
weiroll_py-0.2.2.dist-info/METADATA
weiroll_py-0.2.2.dist-info/WHEEL
weiroll_py-0.2.2.dist-info/RECORD
